tree-viewer/__init__.py
tree-viewer/main.py
tree_viewer/__init__.py
tree_viewer/main.py
tree_viewer-0.1.1.dist-info/LICENSE
tree_viewer-0.1.1.dist-info/METADATA
tree_viewer-0.1.1.dist-info/WHEEL
tree_viewer-0.1.1.dist-info/entry_points.txt
tree_viewer-0.1.1.dist-info/top_level.txt
tree_viewer-0.1.1.dist-info/RECORD
