Metadata-Version: 2.1
Name: tree-viewer
Version: 0.1.1
Summary: Tree-Viewer is a Python tool for generating customizable visual representations of directory trees, ideal for developers who need to manage and navigate complex project structures. It offers a clear, structured view of directory contents, enhancing project organization and accessibility.
Home-page: https://github.com/wiliancirillo/tree-viewer
Author: Wilian Cirillo
Author-email: wilian@hey.com
License: MIT
Classifier: Programming Language :: Python :: 3
Classifier: License :: OSI Approved :: MIT License
Classifier: Operating System :: OS Independent
License-File: LICENSE
